shopagent/__init__.py
shopify_graphql-0.1.0.dist-info/licenses/LICENSE.txt
shopify_graphql-0.1.0.dist-info/METADATA
shopify_graphql-0.1.0.dist-info/WHEEL
shopify_graphql-0.1.0.dist-info/top_level.txt
shopify_graphql-0.1.0.dist-info/RECORD
