Metadata-Version: 2.4
Name: shopify-graphql
Version: 0.1.0
Summary: Add your description here
Requires-Python: >=3.9
License-File: LICENSE.txt
Requires-Dist: fastapi>=0.115.12
Requires-Dist: ollama>=0.4.8
Requires-Dist: psycopg2-binary>=2.9.10
Requires-Dist: pydantic>=2.11.3
Requires-Dist: requests>=2.32.3
Requires-Dist: rich>=14.0.0
Requires-Dist: urllib3==1.26.15
Requires-Dist: whoosh>=2.7.4
Dynamic: license-file
